exchange_ob/__init__.py
exchange_ob/config/__init__.py
exchange_ob/config/config.py
exchange_ob/exchanges/__init__.py
exchange_ob/exchanges/order_book.py
exchange_ob/exchanges/binance/__init__.py
exchange_ob/exchanges/binance/binance.py
exchange_ob/exchanges/bitmart/__init__.py
exchange_ob/exchanges/bitmart/bitmart.py
exchange_ob/exchanges/kucoin/__init__.py
exchange_ob/exchanges/kucoin/kucoin.py
exchange_ob-0.0.2.dist-info/LICENSE
exchange_ob-0.0.2.dist-info/METADATA
exchange_ob-0.0.2.dist-info/WHEEL
exchange_ob-0.0.2.dist-info/top_level.txt
exchange_ob-0.0.2.dist-info/RECORD
